{
  "id": "fd851f63-bb94-4194-8e9f-38299be13849",
  "title": "BasicStrategy",
  "description": "",
  "root": "f8260eb4-7b76-435e-9748-7c540f69475c",
  "properties": {},
  "nodes": {
    "0a76eaf4-7f53-4825-823b-c3b59b2974aa": {
      "id": "0a76eaf4-7f53-4825-823b-c3b59b2974aa",
      "name": "Sequence",
      "title": "Sequence",
      "description": "",
      "properties": {},
      "display": {
        "x": -168,
        "y": -288
      },
      "children": [
        "dd5d7129-39e3-4d09-8183-ecda7e7b3202",
        "51e3456a-13c2-46d9-b923-ec4e6c8e0ef2"
      ]
    },
    "51e3456a-13c2-46d9-b923-ec4e6c8e0ef2": {
      "id": "51e3456a-13c2-46d9-b923-ec4e6c8e0ef2",
      "name": "BasicAttackTactic",
      "title": "BasicAttackTactic",
      "description": "",
      "properties": {},
      "display": {
        "x": 48,
        "y": -192
      }
    },
    "15e192e3-ce42-4578-b5ba-d76694d6f502": {
      "id": "15e192e3-ce42-4578-b5ba-d76694d6f502",
      "name": "BasicDefenseTactic",
      "title": "BasicDefenseTactic",
      "description": "",
      "properties": {},
      "display": {
        "x": -120,
        "y": -72
      }
    },
    "dd5d7129-39e3-4d09-8183-ecda7e7b3202": {
      "id": "dd5d7129-39e3-4d09-8183-ecda7e7b3202",
      "name": "BallOnOurSide",
      "title": "BallOnOurSide_first",
      "description": "",
      "properties": {},
      "display": {
        "x": 48,
        "y": -288
      }
    },
    "f8260eb4-7b76-435e-9748-7c540f69475c": {
      "id": "f8260eb4-7b76-435e-9748-7c540f69475c",
      "name": "Priority",
      "title": "Priority",
      "description": "",
      "properties": {},
      "display": {
        "x": -348,
        "y": -72
      },
      "children": [
        "0a76eaf4-7f53-4825-823b-c3b59b2974aa",
        "15e192e3-ce42-4578-b5ba-d76694d6f502"
      ]
    }
  },
  "display": {
    "camera_x": 927.5,
    "camera_y": 495,
    "camera_z": 1,
    "x": -504,
    "y": -72
  },
  "custom_nodes": [
    {
      "name": "BallOnOurSide",
      "category": "condition",
      "title": "BallOnOurSide",
      "description": null,
      "properties": {}
    },
    {
      "name": "BasicAttackTactic",
      "category": "action",
      "title": "BasicAttackTactic",
      "description": null,
      "properties": {}
    },
    {
      "name": "BasicDefenseTactic",
      "category": "action",
      "title": "BasicDefenseTactic",
      "description": null,
      "properties": {}
    },
    {
      "name": "Repeat",
      "category": "decorator",
      "title": "Repeat",
      "description": null,
      "properties": {}
    },
    {
      "name": "GoToPos",
      "category": "action",
      "title": "GoToPos",
      "description": null,
      "properties": {}
    }
  ]
}
