{
  "id": "24b55629-a01e-4b1e-8a60-a8658e8e0e28",
  "title": "Passer",
  "description": "",
  "root": "e8cbd472-b16a-4315-8883-2e092ca8cd69",
  "properties": {},
  "nodes": {
    "6c419ef7-fe5f-4f29-aaa1-e8db880377fb": {
      "id": "6c419ef7-fe5f-4f29-aaa1-e8db880377fb",
      "name": "GetBall",
      "title": "GetBall_B",
      "description": "",
      "properties": {
        "getBallAtX": "",
        "getBallAtY": "",
        "getBallAtTime": ""
      },
      "display": {
        "x": 252,
        "y": -48
      }
    },
    "11a15123-42d1-4f67-9d08-2d0368d5b04a": {
      "id": "11a15123-42d1-4f67-9d08-2d0368d5b04a",
      "name": "Sequence",
      "title": "Sequence",
      "description": "",
      "properties": {},
      "display": {
        "x": 84,
        "y": 24
      },
      "children": [
        "6c419ef7-fe5f-4f29-aaa1-e8db880377fb",
        "e4a89447-5fba-4611-841e-c2a33483117c",
        "ce757864-d6a5-4b9e-825a-f4f6390cec30",
        "7fdd92f2-fd2e-48ef-857b-f45a4f87b3aa"
      ]
    },
    "e4a89447-5fba-4611-841e-c2a33483117c": {
      "id": "e4a89447-5fba-4611-841e-c2a33483117c",
      "name": "CanSeeRobot",
      "title": "CanSeeRobot_B",
      "description": "",
      "properties": {},
      "display": {
        "x": 252,
        "y": 24
      }
    },
    "ce757864-d6a5-4b9e-825a-f4f6390cec30": {
      "id": "ce757864-d6a5-4b9e-825a-f4f6390cec30",
      "name": "AimAt",
      "title": "AimAt_B",
      "description": "",
      "properties": {
        "At": ""
      },
      "display": {
        "x": 264,
        "y": 84
      }
    },
    "7fdd92f2-fd2e-48ef-857b-f45a4f87b3aa": {
      "id": "7fdd92f2-fd2e-48ef-857b-f45a4f87b3aa",
      "name": "Kick",
      "title": "Kick_B",
      "description": "",
      "properties": {},
      "display": {
        "x": 276,
        "y": 144
      }
    },
    "e8cbd472-b16a-4315-8883-2e092ca8cd69": {
      "id": "e8cbd472-b16a-4315-8883-2e092ca8cd69",
      "name": "RepeatUntilSuccess",
      "title": "Repeat Until Success",
      "description": "",
      "properties": {
        "maxLoop": -1
      },
      "display": {
        "x": -84,
        "y": 24
      },
      "child": "11a15123-42d1-4f67-9d08-2d0368d5b04a"
    }
  },
  "display": {
    "camera_x": 869.7749999976013,
    "camera_y": 216.8199999983599,
    "camera_z": 1,
    "x": -456,
    "y": -84
  },
  "custom_nodes": [
    {
      "name": "BallOnOurSide",
      "category": "condition",
      "title": "BallOnOurSide",
      "description": null,
      "properties": {}
    },
    {
      "name": "BasicAttackTactic",
      "category": "action",
      "title": "BasicAttackTactic",
      "description": null,
      "properties": {}
    },
    {
      "name": "BasicDefenseTactic",
      "category": "action",
      "title": "BasicDefenseTactic",
      "description": null,
      "properties": {}
    },
    {
      "name": "Repeat",
      "category": "decorator",
      "title": "Repeat",
      "description": null,
      "properties": {}
    },
    {
      "name": "GoToPos",
      "category": "action",
      "title": "GoToPos",
      "description": null,
      "properties": {}
    },
    {
      "name": "RotateAroundPoint",
      "category": "action",
      "title": "RotateAroundPoint_A",
      "description": null,
      "properties": {}
    },
    {
      "name": "IHaveBall",
      "category": "condition",
      "title": "IHaveBall_A",
      "description": null,
      "properties": {}
    },
    {
      "name": "GetBall",
      "category": "action",
      "title": "GetBall_B",
      "description": null,
      "properties": {}
    },
    {
      "name": "StandFree",
      "category": "action",
      "title": "StandFree_B",
      "description": null,
      "properties": {}
    },
    {
      "name": "AimAt",
      "category": "action",
      "title": "AimAt_B",
      "description": null,
      "properties": {}
    },
    {
      "name": "Kick",
      "category": "action",
      "title": "Kick_B",
      "description": null,
      "properties": {}
    },
    {
      "name": "CanSeeTheirGoal",
      "category": "condition",
      "title": "CanSeeTheirGoal_B",
      "description": null,
      "properties": {}
    },
    {
      "name": "CanSeeRobot",
      "category": "condition",
      "title": "CanSeeRobot_B",
      "description": null,
      "properties": {}
    },
    {
      "name": "GoToSideTactic",
      "category": "action",
      "title": "GoToSideTactic",
      "description": null,
      "properties": {
        "left": "true"
      }
    },
    {
      "name": "AvoidRobots",
      "category": "action",
      "title": "AvoidRobots",
      "description": null,
      "properties": {}
    },
    {
      "name": "ParallelSequence",
      "category": "composite",
      "title": "ParallelSequence",
      "description": null,
      "properties": {}
    },
    {
      "name": "ParallelTactic",
      "category": "composite",
      "title": "ParallelTactic",
      "description": null,
      "properties": {}
    },
    {
      "name": "DemoTactic",
      "category": "action",
      "title": "DemoTactic",
      "description": null,
      "properties": {}
    },
    {
      "name": "KeeperBlock",
      "category": "action",
      "title": "KeeperBlock",
      "description": null,
      "properties": {}
    },
    {
      "name": "DistanceXToY",
      "category": "condition",
      "title": "DistanceToBall",
      "description": null,
      "properties": {}
    },
    {
      "name": "NaiveBlockGoal",
      "category": "action",
      "title": "NaiveBlockGoal",
      "description": null,
      "properties": {}
    },
    {
      "name": "ParamCheck",
      "category": "condition",
      "title": "ParamCheck",
      "description": null,
      "properties": {}
    },
    {
      "name": "ParamSet",
      "category": "action",
      "title": "ParamSet",
      "description": null,
      "properties": {}
    },
    {
      "name": "AttackerTactic",
      "category": "action",
      "title": "AttackerTactic",
      "description": null,
      "properties": {}
    },
    {
      "name": "BasicKeeperTactic",
      "category": "action",
      "title": "BasicKeeperTactic",
      "description": null,
      "properties": {}
    },
    {
      "name": "BackUp",
      "category": "action",
      "title": "BackUp",
      "description": null,
      "properties": {}
    },
    {
      "name": "Block",
      "category": "action",
      "title": "Block",
      "description": null,
      "properties": {}
    },
    {
      "name": "Chip",
      "category": "action",
      "title": "Chip",
      "description": null,
      "properties": {}
    },
    {
      "name": "Dribble",
      "category": "action",
      "title": "Dribble",
      "description": null,
      "properties": {}
    },
    {
      "name": "FollowPath",
      "category": "action",
      "title": "FollowPath",
      "description": null,
      "properties": {}
    },
    {
      "name": "RandomDrive",
      "category": "action",
      "title": "RandomDrive",
      "description": null,
      "properties": {}
    },
    {
      "name": "SecondaryKeeper",
      "category": "action",
      "title": "SecondaryKeeper",
      "description": null,
      "properties": {}
    },
    {
      "name": "Sleep",
      "category": "action",
      "title": "Sleep",
      "description": null,
      "properties": {}
    },
    {
      "name": "CanInterceptBall",
      "category": "condition",
      "title": "CanInterceptBall",
      "description": null,
      "properties": {}
    },
    {
      "name": "CanPassSafely",
      "category": "condition",
      "title": "CanPassSafely",
      "description": null,
      "properties": {}
    },
    {
      "name": "CanReachPoint",
      "category": "condition",
      "title": "CanReachPoint",
      "description": null,
      "properties": {}
    },
    {
      "name": "CanSeePoint",
      "category": "condition",
      "title": "CanSeePoint",
      "description": null,
      "properties": {}
    },
    {
      "name": "IsBallInGoal",
      "category": "condition",
      "title": "IsBallInGoal",
      "description": null,
      "properties": {}
    },
    {
      "name": "TeamHasBall",
      "category": "condition",
      "title": "TeamHasBall",
      "description": null,
      "properties": {}
    },
    {
      "name": "TheyHaveBall",
      "category": "condition",
      "title": "TheyHaveBall",
      "description": null,
      "properties": {}
    },
    {
      "name": "WeHaveBall",
      "category": "condition",
      "title": "WeHaveBall",
      "description": null,
      "properties": {}
    },
    {
      "name": "BallInsideField",
      "category": "condition",
      "title": "BallInsideField",
      "description": null,
      "properties": {}
    },
    {
      "name": "BallOutsideField",
      "category": "condition",
      "title": "BallOutsideField",
      "description": null,
      "properties": {}
    },
    {
      "name": "OneRobotGetsBallTactic",
      "category": "action",
      "title": "OneRobotGetsBallTactic",
      "description": null,
      "properties": {}
    },
    {
      "name": "DribbleCurve",
      "category": "action",
      "title": "DribbleCurve",
      "description": null,
      "properties": {}
    },
    {
      "name": "IsRefCommand",
      "category": "condition",
      "title": "IsRefCommand",
      "description": null,
      "properties": {}
    },
    {
      "name": "IsRefStage",
      "category": "condition",
      "title": "IsRefStage",
      "description": null,
      "properties": {}
    },
    {
      "name": "ShootAtGoal",
      "category": "action",
      "title": "ShootAtGoal_B",
      "description": null,
      "properties": {}
    },
    {
      "name": "IsBallInZone",
      "category": "condition",
      "title": "IsBallInZone",
      "description": null,
      "properties": {}
    },
    {
      "name": "PassToTactic",
      "category": "action",
      "title": "PassToTactic",
      "description": null,
      "properties": {}
    }
  ]
}
